      Decompiling: 1-st version (without any changes in code) :

C:\Users\PC\Desktop\Internship tasks\b_bytecode\src\main\java>javap -c com\eugeneLevchenko\b_bytecode\App
Compiled from "App.java"
public class com.eugeneLevchenko.b_bytecode.App {
  public com.eugeneLevchenko.b_bytecode.App();
    Code:
       0: aload_0
       1: invokespecial #1                  // Method java/lang/Object."<init>":()V
       4: return

  public static void main(java.lang.String[]);
    Code:
       0: iconst_0                          // load the int value 0 onto the stack
       1: istore_1                          // store int value into variable 1
       2: iload_1                           // load an int value from local variable 1
       3: iconst_5                          // load the int value 5 onto the stack
       4: if_icmpge     16                  // if value1 is greater than or equal to value2, branch to instruction at branchoffset (signed short constructed from unsigned bytes branchbyte1 << 8 + branchbyte2)
       7: iinc          1, 1                // increment local variable #index by signed byte cons
      10: iinc          1, 1
      13: goto          2                   // goes to another instruction at branchoffset (signed short constructed from unsigned bytes branchbyte1 << 8 + branchbyte2)
      16: invokestatic  #2                  // Method experimentalMethod:()V
      19: getstatic     #3                  // Field java/lang/System.out:Ljava/io/PrintStream;
      22: ldc           #4                  // String Hi Eugene
      24: invokevirtual #5                  // Method java/io/PrintStream.println:(Ljava/lang/String;)V
      27: return
}

      Decompiling: 2-nd version [were changed:
1)int i: 5          -> 10
2)Static method     -> Non Static
3)String: Hi Eugene -> Hi Stranger
] :

C:\Users\PC\Desktop\Internship tasks\b_bytecode\src\main\java>javap -c com\eugeneLevchenko\b_bytecode\App
Compiled from "App.java"
public class com.eugeneLevchenko.b_bytecode.App {
  public com.eugeneLevchenko.b_bytecode.App();
    Code:
       0: aload_0
       1: invokespecial #1                  // Method java/lang/Object."<init>":()V
       4: return

  public static void main(java.lang.String[]);
    Code:
       0: iconst_0                          // load the int value 0 onto the stack
       1: istore_1                          // store int value into variable 1
       2: iload_1                           // load an int value from local variable 1
       3: bipush        10                  // push a byte onto the stack as an integer value
       5: if_icmpge     17                  // if value1 is greater than or equal to value2, branch to instruction at branchoffset (signed short constructed from unsigned bytes branchbyte1 << 8 + branchbyte2)
       8: iinc          1, 1                // increment local variable #index by signed byte const
      11: iinc          1, 1 
      14: goto          2                   // goes to another instruction at branchoffset (signed short constructed from unsigned bytes branchbyte1 << 8 + branchbyte2)
      17: new           #2                  // class com/eugeneLevchenko/b_bytecode/App
      20: dup                               // duplicate the value on top of the stack
      21: invokespecial #3                  // Method "<init>":()V
      24: astore_1                          // store a reference into local variable 1
      25: aload_1                           // load a reference onto the stack from local variable 1
      26: invokespecial #4                  // Method experimentalMethod:()V
      29: getstatic     #5                  // Field java/lang/System.out:Ljava/io/PrintStream;
      32: ldc           #6                  // String Hi Stranger
      34: invokevirtual #7                  // Method java/io/PrintStream.println:(Ljava/lang/String;)V
      37: return
}

Brief Description:
1)For both code versions compiler calls the default constructor (as written in the JVM specifications)
2)"for" Loop
3)increment
4)call method
5)print msg to console 

Commands of cmd script:
1.Go to necessary directory         -> cd yourDir
2.Compile Class                     -> javac YourClass.java
3.Run Java program                  -> java YourClass
4.Decompile .class file to Bytecode -> javap -c YourClass